{
  "$schema": "https://schema.management.azure.com/schemas/2019-04-01/deploymentParameters.json#",
  "contentVersion": "1.0.0.0",
  "parameters": {
    "environmentName": {
      "value": "copa-devops-validation"
    },
    "location": {
      "value": "uksouth"
    },
    "principalId": {
      "value": "00000000-0000-0000-0000-000000000000"
    },
    "environmentCode": {
      "value": "d"
    },
    "instanceNumber": {
      "value": "001"
    },
    "enablePrivateEndpoints": {
      "value": true
    },
    "vnetAddressPrefix": {
      "value": "10.0.0.0/16"
    },
    "appServiceSubnetAddressPrefix": {
      "value": "10.0.1.0/24"
    },
    "privateEndpointSubnetAddressPrefix": {
      "value": "10.0.2.0/24"
    },
    "ownerTag": {
      "value": "DevOps-Pipeline"
    },
    "costCentreTag": {
      "value": "IT-001"
    },
    "forceIdTag": {
      "value": "BTP"
    },
    "serviceNameTag": {
      "value": "CoPA-Stop-Search"
    },
    "locationIdTag": {
      "value": "UK-South"
    },
    "environmentTag": {
      "value": "Development"
    }
  }
}